leaf/__init__.py
leaf/data_prep.py
leaf/generate_sheets.py
leaf/inference.py
leaf/metrics.py
leaf/models.py
leaf/visualization.py
leaf/config/__init__.py
leaf/config/canopy_landscape.yaml
leaf/config/canopy_portrait.yaml
leaf/config/flatbed.yaml
leaf/config/flattened_leaves.yaml
leaf_toolkit-1.0.0.dist-info/licenses/LICENSE
leaf_toolkit-1.0.0.dist-info/METADATA
leaf_toolkit-1.0.0.dist-info/WHEEL
leaf_toolkit-1.0.0.dist-info/top_level.txt
leaf_toolkit-1.0.0.dist-info/RECORD
