Metadata-Version: 2.4
Name: leaf-toolkit
Version: 1.0.0
Summary: Leaf Analysis and Evaluation Toolkit
Author-email: Radek Zenkl <radek.zenkl@usys.ethz.ch>
Maintainer-email: Radek Zenkl <radek.zenkl@usys.ethz.ch>
License-Expression: GPL-3.0-or-later
Project-URL: Homepage, https://github.com/RadekZenkl/leaf-toolkit
Project-URL: Bug Reports, https://github.com/RadekZenkl/leaf-toolkit/issues
Project-URL: Source, https://github.com/RadekZenkl/leaf-toolkit
Classifier: Development Status :: 3 - Alpha
Classifier: Intended Audience :: Science/Research
Classifier: Programming Language :: Python :: 3
Classifier: Programming Language :: Python :: 3.12
Classifier: Programming Language :: Python :: 3.13
Requires-Python: >=3.12
License-File: LICENSE
Requires-Dist: setuptools>=64.0
Requires-Dist: ultralytics>=8.3.107
Requires-Dist: opencv-python
Requires-Dist: scikit-image
Requires-Dist: torch>=2.0.1
Requires-Dist: torchvision
Requires-Dist: torchmetrics
Requires-Dist: matplotlib
Requires-Dist: mpldatacursor
Requires-Dist: mplcursors
Requires-Dist: protobuf
Requires-Dist: tqdm
Requires-Dist: psutil
Requires-Dist: hydra-core>=1.3.2
Requires-Dist: omegaconf>=2.3.0
Dynamic: license-file
